jwstnoobfriend/__init__.py
jwstnoobfriend/py.typed
jwstnoobfriend/cli/__init__.py
jwstnoobfriend/cli/env.py
jwstnoobfriend/cli/fetch.py
jwstnoobfriend/cli/script.py
jwstnoobfriend/navigation/__init__.py
jwstnoobfriend/navigation/_cache.py
jwstnoobfriend/navigation/filebox.py
jwstnoobfriend/navigation/footprint.py
jwstnoobfriend/navigation/jwstinfo.py
jwstnoobfriend/reduction/__init__.py
jwstnoobfriend/reduction/stage2.py
jwstnoobfriend/templates/all_1b_2a.py.jinja2
jwstnoobfriend/templates/all_2a.toml.jinja2
jwstnoobfriend/templates/clear_2*_3a.py.jinja2
jwstnoobfriend/templates/clear_2a_2b.py.jinja2
jwstnoobfriend/templates/clear_2b.toml.jinja2
jwstnoobfriend/templates/clear_2b_2bi.py.jinja2
jwstnoobfriend/templates/clear_3a.toml.jinja2
jwstnoobfriend/templates/reduction_init.env.jinja2
jwstnoobfriend/templates/reduction_storage.env.jinja2
jwstnoobfriend/utils/__init__.py
jwstnoobfriend/utils/calculate.py
jwstnoobfriend/utils/display.py
jwstnoobfriend/utils/environment.py
jwstnoobfriend/utils/extraction.py
jwstnoobfriend/utils/io.py
jwstnoobfriend/utils/log.py
jwstnoobfriend/utils/network.py
jwstnoobfriend-0.2.0.dist-info/METADATA
jwstnoobfriend-0.2.0.dist-info/WHEEL
jwstnoobfriend-0.2.0.dist-info/entry_points.txt
jwstnoobfriend-0.2.0.dist-info/RECORD
