Metadata-Version: 2.4
Name: jwstnoobfriend
Version: 0.2.0
Summary: Not Only Observational Bundle: For Reduction, Inference, Extraction & Navigation of Data (JWST/WFSS)
Author-email: Chenghao Zhu <zchao@icrr.u-tokyo.ac.jp>
Requires-Python: >=3.13
Requires-Dist: aiofiles>=24.1.0
Requires-Dist: aiohttp>=3.12.13
Requires-Dist: anywidget>=0.9.18
Requires-Dist: astropy>=7.1.0
Requires-Dist: astroquery>=0.4.10
Requires-Dist: asyncer>=0.0.8
Requires-Dist: cachetools>=6.1.0
Requires-Dist: dash>=3.1.1
Requires-Dist: jwst>=1.18.0
Requires-Dist: matplotlib>=3.10.3
Requires-Dist: networkx>=3.5
Requires-Dist: numpy>=2.2.0
Requires-Dist: plotly>=6.2.0
Requires-Dist: pydantic>=2.11.5
Requires-Dist: python-dotenv>=1.1.1
Requires-Dist: requests>=2.32.3
Requires-Dist: rich>=14.0.0
Requires-Dist: scipy>=1.15.3
Requires-Dist: seaborn>=0.13.2
Requires-Dist: shapely>=2.1.1
Requires-Dist: typer>=0.16.0
